<PAMDataset>
  <PAMRasterBand band="1">
    <Histograms>
      <HistItem>
        <HistMin>-0.01208500003814697</HistMin>
        <HistMax>24.18208507633209</HistMax>
        <BucketCount>1000</BucketCount>
        <IncludeOutOfRange>0</IncludeOutOfRange>
        <Approximate>1</Approximate>
        <HistCounts>29989|0|0|0|0|0|0|0|0|0|0|0|0|0|0|0|0|0|0|0|0|0|0|0|0|0|0|0|0|0|0|0|0|0|0|0|0|0|0|0|0|0|0|0|0|0|0|0|0|0|0|0|0|0|0|0|0|0|0|0|0|0|0|0|0|0|0|0|0|0|0|0|0|0|0|0|0|0|0|0|0|0|0|0|0|0|1|0|2|0|1|1|1|1|1|0|0|0|1|0|1|0|1|4|2|1|0|2|2|2|2|2|1|0|3|0|2|1|2|2|1|0|2|2|3|2|0|1|1|3|1|4|1|1|3|3|1|2|4|3|1|8|1|3|1|6|1|2|2|4|8|2|2|3|2|4|5|6|2|1|3|4|3|3|4|4|2|6|6|6|3|3|6|7|6|6|6|3|2|6|4|7|3|5|7|3|8|2|5|3|4|4|4|10|2|3|2|4|3|7|6|2|4|7|5|2|2|2|2|4|3|9|6|13|9|3|9|16|6|12|9|9|11|8|14|12|10|19|8|9|8|9|6|8|12|9|10|9|9|7|3|13|11|10|8|9|7|7|10|11|16|10|8|13|8|7|6|13|11|7|9|8|12|13|11|17|8|11|8|12|7|9|18|8|19|7|6|17|7|12|14|22|7|7|14|7|16|10|9|15|12|17|9|16|13|10|17|11|17|6|12|10|5|7|7|16|9|9|15|4|9|9|19|8|6|12|12|17|9|21|12|7|17|7|12|6|5|13|10|13|9|20|10|11|11|6|12|7|7|18|12|15|5|13|7|4|14|7|11|6|10|5|13|9|4|13|6|7|14|9|19|6|11|7|10|6|9|8|10|7|7|6|6|3|14|6|9|8|3|6|4|7|3|9|14|6|9|11|5|8|3|5|9|7|2|7|6|7|6|6|7|5|6|7|4|7|1|3|5|2|5|5|3|3|4|4|1|5|4|6|11|9|14|4|7|10|8|7|14|14|10|7|13|12|9|6|6|5|8|5|2|7|11|7|2|6|8|5|16|2|5|10|5|7|4|7|2|5|11|5|4|6|3|5|1|3|5|6|2|4|6|3|4|7|14|7|1|7|3|6|3|3|8|5|7|6|6|4|2|4|4|3|3|4|3|2|2|1|3|4|2|6|3|5|2|2|3|5|6|2|6|3|3|8|3|3|1|1|1|3|3|3|6|2|0|2|1|3|4|1|2|2|3|1|1|0|2|1|0|2|1|4|2|2|2|0|1|1|0|2|2|0|1|0|0|2|0|1|3|1|0|3|3|1|0|3|1|0|3|1|1|1|1|1|0|2|2|1|0|2|1|2|2|0|0|2|1|1|0|1|2|1|3|0|0|3|2|0|0|2|1|0|1|1|1|0|0|1|0|1|1|1|0|0|1|0|2|0|0|0|0|0|1|0|1|0|0|0|0|0|0|1|1|0|0|0|2|0|0|1|1|0|2|0|0|0|2|1|0|1|0|0|0|1|1|0|1|1|0|0|0|1|0|0|1|3|0|1|0|0|0|1|0|0|0|0|0|0|0|0|0|0|0|1|0|0|0|0|0|0|0|1|0|0|0|0|0|0|0|0|0|0|0|0|0|0|1|0|1|0|0|0|0|1|0|1|1|0|0|1|0|0|0|0|0|0|0|0|0|0|0|1|0|0|0|0|0|0|0|0|0|0|0|0|0|0|1|0|0|1|0|0|0|0|0|0|0|0|1|0|0|0|0|0|0|0|0|1|0|1|0|0|0|0|0|0|0|0|0|0|0|1|0|0|1|0|0|1|0|0|0|0|0|1|0|1|0|1|0|0|0|0|0|0|0|0|0|0|0|0|0|0|0|0|0|0|0|0|0|0|0|0|0|0|0|0|0|0|0|0|0|0|1|0|0|0|0|0|0|0|0|0|0|0|0|0|0|0|0|1|0|0|0|0|0|0|0|0|0|0|0|0|0|0|0|0|0|0|0|0|0|0|0|0|0|0|0|0|0|0|0|0|0|0|0|0|0|0|0|0|0|0|0|0|0|0|0|0|0|0|0|0|0|0|0|0|0|0|0|0|0|0|0|0|0|0|0|0|0|0|0|0|0|0|0|0|0|0|0|0|0|0|0|0|0|0|0|0|0|0|0|0|0|0|0|0|0|0|0|0|0|0|0|0|0|0|0|0|0|0|0|0|0|0|0|0|0|0|0|0|1|0|0|0|0|0|0|0|0|0|0|0|0|0|0|0|0|0|0|0|0|1|0|0|0|0|0|0|0|1</HistCounts>
      </HistItem>
    </Histograms>
    <Metadata>
      <MDI key="STATISTICS_MAXIMUM">24.170000076294</MDI>
      <MDI key="STATISTICS_MEAN">0.73672543856592</MDI>
      <MDI key="STATISTICS_MINIMUM">0</MDI>
      <MDI key="STATISTICS_STDDEV">2.4771922752301</MDI>
    </Metadata>
  </PAMRasterBand>
</PAMDataset>
